async_runner/__init__.py
async_runner/async_runner.py
async_runner-0.1.2.dist-info/DESCRIPTION.rst
async_runner-0.1.2.dist-info/METADATA
async_runner-0.1.2.dist-info/RECORD
async_runner-0.1.2.dist-info/WHEEL
async_runner-0.1.2.dist-info/metadata.json
async_runner-0.1.2.dist-info/top_level.txt
