Metadata-Version: 2.0
Name: async-runner
Version: 0.1.2
Summary: Async Runner
Home-page: https://github.com/vedarthk/async_runner
Author: Vedarth Kulkarni
Author-email: vedarthk@vedarthz.in
License: MIT
Keywords: async_runner
Platform: UNKNOWN
Classifier: Development Status :: 2 - Pre-Alpha
Classifier: Intended Audience :: Developers
Classifier: License :: OSI Approved :: MIT License
Classifier: Natural Language :: English
Classifier: Programming Language :: Python :: 3.5
Requires-Dist: celery (>=3.1.20)
